[
   {
     "id": 999999,
     "from": {
       "name": "Tom Brady"
     },
     "message": "Looking forward to 2010!",
     "actions": [
       {
         "name": "Comment",
         "link": "http://www.facebook.com/X999/posts/Y999"
       },
       {
         "name": "Like",
         "link": "http://www.facebook.com/X999/posts/Y999"
       }
     ],
     "type": "status",
     "created_time": "2010-08-02T21:27:44+0000",
     "updated_time": "2010-08-02T21:27:44+0000"
   },
   {
     "id": 998998,
     "from": {
       "name": "Peyton Manning"
     },
     "message": "Where's my contract?",
     "actions": [
       {
         "name": "Comment",
         "link": "http://www.facebook.com/X998/posts/Y998"
       },
       {
         "name": "Like",
         "link": "http://www.facebook.com/X998/posts/Y998"
       }
     ],
     "type": "status",
     "created_time": "2010-08-02T21:27:44+0000",
     "updated_time": "2010-08-02T21:27:44+0000"
   }
 ]
 
